rfmetadata/__init__.py
rfmetadata/__main__.py
rfmetadata/main.py
rfmetadata/readme.md
rfmetadata/signal_manager/__init__.py
rfmetadata/signal_manager/data_signal_manager.py
rfmetadata/version.py
rfmetadata/widgets/__init__.py
rfmetadata/widgets/data_graph_layout.py
rfmetadata/widgets/query_result_layout.py
rfmetadata/widgets/search_layout.py
rfmetadata/windows/__init__.py
rfmetadata/windows/main_window.py
rfmetadata/windows/query_result_window.py
rfmetadata-1.0.0.dist-info/AUTHORS.md
rfmetadata-1.0.0.dist-info/LICENSE
rfmetadata-1.0.0.dist-info/METADATA
rfmetadata-1.0.0.dist-info/WHEEL
rfmetadata-1.0.0.dist-info/entry_points.txt
rfmetadata-1.0.0.dist-info/RECORD
