Metadata-Version: 2.3
Name: rfmetadata
Version: 1.0.0
Summary: RF MetaData Displayer
License: AGPL-3.0-only
Keywords: Radio Frequency,RF,Node
Author: Iso
Maintainer: Iso
Requires-Python: >=3.8
Classifier: Development Status :: 5 - Production/Stable
Classifier: Intended Audience :: Manufacturing
Classifier: Intended Audience :: Other Audience
Classifier: License :: OSI Approved :: GNU Affero General Public License v3
Classifier: Natural Language :: English
Classifier: Operating System :: Unix
Classifier: Operating System :: POSIX :: Linux
Classifier: Operating System :: MacOS
Classifier: Programming Language :: Python :: 3 :: Only
Classifier: Programming Language :: Python :: 3.8
Classifier: Programming Language :: Python :: 3.9
Classifier: Programming Language :: Python :: 3.10
Classifier: Programming Language :: Python :: 3.11
Classifier: Programming Language :: Python :: 3.12
Classifier: Programming Language :: Python :: 3.13
Classifier: Topic :: Desktop Environment
Provides-Extra: docs
Provides-Extra: test
Requires-Dist: Sphinx (<=8.2.3) ; (python_version >= "3.11" and python_version <= "3.14") and (extra == "docs")
Requires-Dist: flask
Requires-Dist: matplotlib (>=3.10.1) ; python_version >= "3.10" and python_version <= "3.13"
Requires-Dist: pyside6
Requires-Dist: pytest (>=8.4.0) ; (python_version >= "3.9" and python_version <= "3.14") and (extra == "test")
Requires-Dist: pytest-cov (>=6) ; (python_version >= "3.9" and python_version <= "3.13") and (extra == "test")
Requires-Dist: pytest-mock (>=3.14.0) ; (python_version >= "3.9" and python_version <= "3.14") and (extra == "test")
Requires-Dist: scipy
Requires-Dist: sphinx-autobuild (==2024.10.3) ; (python_version >= "3.9" and python_version <= "3.14") and (extra == "docs")
Requires-Dist: sphinx-autodoc-typehints (<=3.2.0) ; (python_version >= "3.11" and python_version <= "3.14") and (extra == "docs")
Requires-Dist: sphinx-inline-tabs (==2023.4.21) ; (python_version >= "3.8" and python_version <= "3.14") and (extra == "docs")
Requires-Dist: sphinx-rtd-theme (<=3.0.2) ; (python_version >= "3.8" and python_version <= "3.14") and (extra == "docs")
Requires-Dist: sphinxcontrib-mermaid (<=1.0.0) ; (python_version >= "3.8" and python_version <= "3.14") and (extra == "docs")
Requires-Dist: sphinxcontrib-spelling (<=8.0.1) ; (python_version >= "3.10" and python_version <= "3.14") and (extra == "docs")
Project-URL: Bug Tracker, https://github.com/alanmehio/rf-metadata-displayer/issues
Project-URL: CI: Github Actions, https://github.com/alanmehio/rf-metadata-displayer/actions
Project-URL: Changelog, https://github.com/alanmehio/rf-metadata-displayer/blob/master/CHANGELOG.rst
Project-URL: Documentation, https://rf-metadata-displayer.readthedocs.io/
Project-URL: Source Code, https://github.com/alanmehio/rf-metadata-displayer
